<?xml version="1.0"?>
<chapters><satusatutiga><pages><path>../manga/Black Clover/113/0.jpg</path></pages><pages><path>../manga/Black Clover/113/1.jpg</path></pages><pages><path>../manga/Black Clover/113/10.jpg</path></pages><pages><path>../manga/Black Clover/113/11.jpg</path></pages><pages><path>../manga/Black Clover/113/12.jpg</path></pages><pages><path>../manga/Black Clover/113/13.jpg</path></pages><pages><path>../manga/Black Clover/113/14.jpg</path></pages><pages><path>../manga/Black Clover/113/15.jpg</path></pages><pages><path>../manga/Black Clover/113/2.jpg</path></pages><pages><path>../manga/Black Clover/113/3.jpg</path></pages><pages><path>../manga/Black Clover/113/4.jpg</path></pages><pages><path>../manga/Black Clover/113/5.jpg</path></pages><pages><path>../manga/Black Clover/113/6.jpg</path></pages><pages><path>../manga/Black Clover/113/7.jpg</path></pages><pages><path>../manga/Black Clover/113/8.jpg</path></pages><pages><path>../manga/Black Clover/113/9.jpg</path></pages></satusatutiga><dua><pages><path>../manga/Black Clover/2/1.jpg</path></pages><pages><path>../manga/Black Clover/2/10.jpg</path></pages><pages><path>../manga/Black Clover/2/11.jpg</path></pages><pages><path>../manga/Black Clover/2/12.jpg</path></pages><pages><path>../manga/Black Clover/2/13.jpg</path></pages><pages><path>../manga/Black Clover/2/14.jpg</path></pages><pages><path>../manga/Black Clover/2/15.jpg</path></pages><pages><path>../manga/Black Clover/2/16.jpg</path></pages><pages><path>../manga/Black Clover/2/17.jpg</path></pages><pages><path>../manga/Black Clover/2/18.jpg</path></pages><pages><path>../manga/Black Clover/2/19.jpg</path></pages><pages><path>../manga/Black Clover/2/2.jpg</path></pages><pages><path>../manga/Black Clover/2/20.jpg</path></pages><pages><path>../manga/Black Clover/2/21.jpg</path></pages><pages><path>../manga/Black Clover/2/22.jpg</path></pages><pages><path>../manga/Black Clover/2/23.jpg</path></pages><pages><path>../manga/Black Clover/2/24.jpg</path></pages><pages><path>../manga/Black Clover/2/25.jpg</path></pages><pages><path>../manga/Black Clover/2/26.jpg</path></pages><pages><path>../manga/Black Clover/2/3.jpg</path></pages><pages><path>../manga/Black Clover/2/4.jpg</path></pages><pages><path>../manga/Black Clover/2/5.jpg</path></pages><pages><path>../manga/Black Clover/2/6.jpg</path></pages><pages><path>../manga/Black Clover/2/7.jpg</path></pages><pages><path>../manga/Black Clover/2/8.jpg</path></pages><pages><path>../manga/Black Clover/2/9.jpg</path></pages></dua></chapters>
